{
    "mu_DSCB_0_2012_GTIS": {
        "value": 5236.832596529172,
        "hesse": {
            "error": 10.735655737909191,
            "cl": 0.68268949
        }
    },
    "sigma_DSCB_0_2012_GTIS": {
        "value": 30.177003658378943,
        "hesse": {
            "error": 6.656909462916164,
            "cl": 0.68268949
        }
    },
    "alphal_DSCB_0_2012_GTIS": {
        "value": 0.28673777855414206,
        "hesse": {
            "error": 0.07700631684054428,
            "cl": 0.68268949
        }
    },
    "nl_DSCB_0_2012_GTIS": {
        "value": 113.80052960934454,
        "hesse": {
            "error": 136.4177964982188,
            "cl": 0.68268949
        }
    },
    "alphar_DSCB_0_2012_GTIS": {
        "value": 3.7989319281755654,
        "hesse": {
            "error": 9.504049895644144,
            "cl": 0.68268949
        }
    },
    "nr_DSCB_0_2012_GTIS": {
        "value": 80.93246413797155,
        "hesse": {
            "error": 4705.786200511123,
            "cl": 0.68268949
        }
    }
}