{"id":"sqlalchemy.sql._typing","path":"/opt/homebrew/Caskroom/miniforge/base/envs/tree/lib/python3.11/site-packages/sqlalchemy/sql/_typing.py","mtime":1717018938,"size":12771,"hash":"a2ac2b60754cb4af80b8a187f5ce1281f88e10952de6f8e4cd2133cec70c1e43","data_mtime":1715816999,"dependencies":["sqlalchemy.sql.roles","sqlalchemy.util.typing","sqlalchemy.sql.base","sqlalchemy.sql.compiler","sqlalchemy.sql.dml","sqlalchemy.sql.elements","sqlalchemy.sql.lambdas","sqlalchemy.sql.schema","sqlalchemy.sql.selectable","sqlalchemy.sql.sqltypes","sqlalchemy.sql.type_api","sqlalchemy.sql","sqlalchemy.exc","sqlalchemy.util","sqlalchemy.inspection","sqlalchemy.engine","__future__","operator","typing","sqlalchemy","datetime","decimal","uuid","builtins","_typeshed","abc","sqlalchemy.engine.interfaces","sqlalchemy.event","sqlalchemy.event.registry","sqlalchemy.sql.annotation","sqlalchemy.sql.cache_key","sqlalchemy.sql.operators","sqlalchemy.sql.traversals","sqlalchemy.sql.visitors","sqlalchemy.util._py_collections","sqlalchemy.util.langhelpers"],"suppressed":[],"options":{"warn_no_return":true,"implicit_optional":false,"disable_memoryview_promotion":false,"follow_imports":"normal","disallow_any_explicit":false,"strict_optional":true,"always_true":[],"disallow_any_decorated":false,"plugins":[],"warn_return_any":false,"strict_equality":false,"mypyc":false,"disallow_subclassing_any":false,"extra_checks":false,"disallow_untyped_calls":false,"allow_untyped_globals":false,"warn_unreachable":false,"strict_concatenate":false,"disallow_untyped_decorators":false,"allow_redefinition":false,"disallow_any_expr":false,"disable_error_code":[],"follow_imports_for_stubs":false,"always_false":[],"disallow_incomplete_defs":false,"warn_unused_ignores":false,"new_type_inference":false,"local_partial_types":false,"enabled_error_codes":[],"disallow_untyped_defs":false,"ignore_errors":false,"disallow_any_generics":false,"implicit_reexport":true,"enable_error_code":[],"ignore_missing_imports":true,"disable_bytearray_promotion":false,"disabled_error_codes":[],"platform":"darwin","bazel":false,"check_untyped_defs":false,"disallow_any_unimported":false},"dep_prios":[10,5,25,25,25,25,25,25,25,25,25,20,10,10,5,25,5,10,5,20,25,25,25,5,30,30,30,30,30,30,30,30,30,30,30,30],"dep_lines":[27,31,43,44,47,49,55,57,58,69,71,27,28,29,30,72,8,10,11,28,36,40,41,1,1,1,1,1,1,1,1,1,1,1,1,1],"interface_hash":"20a73290d906cc3f5f8ef1aca2bf31467ae4c4f0cfd7fd9b19e1c4fe129438f0","version_id":"1.6.0","ignore_all":true,"plugin_data":null}