{
    "frac1_3Gauss_psi2S_Jpsi_2011_GTIS": {
        "value": 0.5577106018294821,
        "hesse": {
            "error": 0.01814215543700302,
            "cl": 0.68268949
        }
    },
    "_frac2_3Gauss_psi2S_Jpsi_2011_GTIS": {
        "value": 0.06360323172720812,
        "hesse": {
            "error": 0.007295922333456827,
            "cl": 0.68268949
        }
    },
    "mu1_3Gauss_psi2S_Jpsi_2011_GTIS": {
        "value": -143.03828797982237,
        "hesse": {
            "error": 1.8378758322597462,
            "cl": 0.68268949
        }
    },
    "sigma1_3Gauss_psi2S_Jpsi_2011_GTIS": {
        "value": 35.12600966979203,
        "hesse": {
            "error": 1.7118186633280759,
            "cl": 0.68268949
        }
    },
    "mu2_3Gauss_psi2S_Jpsi_2011_GTIS": {
        "value": -799.9999969178485,
        "hesse": {
            "error": 0.004948980383766448,
            "cl": 0.68268949
        }
    },
    "sigma2_3Gauss_psi2S_Jpsi_2011_GTIS": {
        "value": 79.99999617881656,
        "hesse": {
            "error": 0.0024052343449523592,
            "cl": 0.68268949
        }
    },
    "mu3_3Gauss_psi2S_Jpsi_2011_GTIS": {
        "value": -317.73358151152064,
        "hesse": {
            "error": 6.278259195582639,
            "cl": 0.68268949
        }
    },
    "sigma3_3Gauss_psi2S_Jpsi_2011_GTIS": {
        "value": 123.5599472040779,
        "hesse": {
            "error": 3.1868973061771393,
            "cl": 0.68268949
        }
    }
}